MANIFEST.in
README.rst
setup.cfg
setup.py
ebay/__init__.py
ebay/best_match.py
ebay/client_alerts.py
ebay/config.ini
ebay/config.ini.example
ebay/feedback.py
ebay/finding.py
ebay/merchandising.py
ebay/platform_notifications.py
ebay/product.py
ebay/research.py
ebay/resolution_case_management.py
ebay/shopping.py
ebay/trading.py
ebay/utils.py
python_ebay.egg-info/PKG-INFO
python_ebay.egg-info/SOURCES.txt
python_ebay.egg-info/dependency_links.txt
python_ebay.egg-info/entry_points.txt
python_ebay.egg-info/not-zip-safe
python_ebay.egg-info/requires.txt
python_ebay.egg-info/top_level.txt