Metadata-Version: 1.1
Name: python-ebay
Version: 0.2.0b5dev
Summary: Python Wrapper for eBay API
Home-page: https://github.com/roopeshvaddepally/python-ebay
Author: Utkarsh Sengar, Roopesh Vaddepally
Author-email: utkarsh2012@gmail.com, roopeshvaddepally@gmail.com
License: Apache Software License
Keywords: ebay api wrapper
Platform: UNKNOWN
Classifier: Development Status :: 4 - Beta
Classifier: Topic :: Internet :: WWW/HTTP :: Dynamic Content
Classifier: License :: OSI Approved :: Apache Software License
